README.txt
setup.cfg
setup.py
docs/HISTORY.txt
docs/INSTALL.txt
docs/LICENSE.GPL
docs/LICENSE.txt
vs/__init__.py
vs.alias.egg-info/PKG-INFO
vs.alias.egg-info/SOURCES.txt
vs.alias.egg-info/dependency_links.txt
vs.alias.egg-info/entry_points.txt
vs.alias.egg-info/namespace_packages.txt
vs.alias.egg-info/not-zip-safe
vs.alias.egg-info/requires.txt
vs.alias.egg-info/top_level.txt
vs/alias/__init__.py
vs/alias/config.py
vs/alias/configure.zcml
vs/alias/skins.zcml
vs/alias/tests.py
vs/alias/version.txt
vs/alias/browser/__init__.py
vs/alias/browser/configure.zcml
vs/alias/browser/views.py
vs/alias/browser/images/alias_icon.gif
vs/alias/browser/templates/__init__.py
vs/alias/browser/templates/alias_view.pt
vs/alias/browser/templates/configure.zcml
vs/alias/content/__init__.py
vs/alias/content/alias.py
vs/alias/content/configure.zcml
vs/alias/interfaces/__init__.py
vs/alias/locales/compile.sh
vs/alias/locales/createlang.sh
vs/alias/locales/createpot.sh
vs/alias/locales/vs.alias.pot
vs/alias/locales/de/LC_MESSAGES/vs.alias.po
vs/alias/profiles/default/factorytool.xml
vs/alias/profiles/default/metadata.xml
vs/alias/profiles/default/types.xml
vs/alias/profiles/default/types/Alias.xml