Metadata-Version: 1.0
Name: vs.alias
Version: 1.2
Summary: An alias add-on for Plone 4
Home-page: http://pypi.python.org/pypi/vs.alias
Author: Veit Schiele, Anne Walther, Andreas Jung
Author-email: vs-alias@veit-schiele.de
License: GPL
Platform: UNKNOWN
Classifier: Framework :: Plone
Classifier: Programming Language :: Python
Classifier: Topic :: Software Development :: Libraries :: Python Modules
